pwp_bench.py
pwp_bench-0.0.1.dist-info/METADATA
pwp_bench-0.0.1.dist-info/WHEEL
pwp_bench-0.0.1.dist-info/licenses/LICENSE
pwp_bench-0.0.1.dist-info/RECORD
