Metadata-Version: 2.4
Name: pwp_bench
Version: 0.0.1
Summary: A python module to generate benchmark datasets for parametric anomaly detection in context-dependent industrial relationships
Project-URL: Homepage, https://github.com/mazenalamir/pwp_bench
Project-URL: Issues, https://github.com/mazenalamir/pwp_bench/issues
Author-email: Mazen Alamir <mazen.alamir@grenoble-inp.fr>
License-Expression: MIT
License-File: LICENSE
Classifier: License :: OSI Approved :: MIT License
Classifier: Operating System :: OS Independent
Classifier: Programming Language :: Python :: 3
Requires-Python: >=3.9
